asyncusb/__init__.py
asyncusb/_libusb.py
asyncusb/_types.py
asyncusb/compat.py
asyncusb/core.py
asyncusb-0.0.2.dist-info/METADATA
asyncusb-0.0.2.dist-info/WHEEL
asyncusb-0.0.2.dist-info/licenses/LICENSE
asyncusb-0.0.2.dist-info/RECORD
