Metadata-Version: 2.4
Name: asyncusb
Version: 0.0.2
Summary: Another async libusb wrapper.
Project-URL: Source, https://github.com/JacobTDC/asyncusb
Project-URL: Issues, https://github.com/JacobTDC/asyncusb/issues
Author: Jacob Story
License-Expression: ISC
License-File: LICENSE
Classifier: Framework :: AsyncIO
Classifier: License :: OSI Approved :: ISC License (ISCL)
Classifier: Operating System :: OS Independent
Classifier: Programming Language :: Python :: 3.12
Classifier: Topic :: System :: Hardware :: Universal Serial Bus (USB)
Requires-Python: >=3.12
